LICENSE
MANIFEST.in
README.rst
setup.py
RecursiveDocument/__init__.py
RecursiveDocument.egg-info/PKG-INFO
RecursiveDocument.egg-info/SOURCES.txt
RecursiveDocument.egg-info/dependency_links.txt
RecursiveDocument.egg-info/top_level.txt
RecursiveDocument/tests/ContentTestCase.py
RecursiveDocument/tests/DefinitionListTestCase.py
RecursiveDocument/tests/IndentationTestCase.py
RecursiveDocument/tests/WrappingTestCase.py
RecursiveDocument/tests/__init__.py