Metadata-Version: 1.1
Name: RecursiveDocument
Version: 0.5.1
Summary: Format, in a console-friendly and human-readable way, a document specified through its structure
Home-page: http://pythonhosted.org/RecursiveDocument/
Author: Vincent Jacques
Author-email: vincent@vincent-jacques.net
License: MIT
Platform: UNKNOWN
Classifier: Development Status :: 4 - Beta
Classifier: License :: OSI Approved
Classifier: License :: OSI Approved :: MIT License
Classifier: Operating System :: OS Independent
Classifier: Programming Language :: Python
Classifier: Programming Language :: Python :: 2
Classifier: Programming Language :: Python :: 2.7
Classifier: Programming Language :: Python :: 3
Classifier: Programming Language :: Python :: 3.3
Classifier: Programming Language :: Python :: 3.4
Classifier: Topic :: Text Processing
Classifier: Topic :: Documentation
Classifier: Topic :: Software Development :: Documentation
Classifier: Environment :: Console
